<!--
WARNING: THIS IS AN AUTO-GENERATED FILE. CHANGES TO IT ARE LIKELY TO BE
OVERWRITTEN AND LOST. Changes to this xml configuration should be made using:
  virsh pool-edit default
or other application using the libvirt API.
-->

<pool type='dir'>
  <name>default</name>
  <uuid>dca07b9f-8f5b-4800-b015-13fcb5abd4e8</uuid>
  <capacity unit='bytes'>0</capacity>
  <allocation unit='bytes'>0</allocation>
  <available unit='bytes'>0</available>
  <source>
  </source>
  <target>
    <path>/home/spect/.vm</path>
  </target>
</pool>
